hexor/__init__.py
hexor/hexorversion.py
hexor-0.0.15.dist-info/LICENSE
hexor-0.0.15.dist-info/METADATA
hexor-0.0.15.dist-info/WHEEL
hexor-0.0.15.dist-info/top_level.txt
hexor-0.0.15.dist-info/RECORD
