Metadata-Version: 2.1
Name: hexor
Version: 0.0.15
Summary: Coloring texts and their backgrounds in command line interface (cli), with rgb or hex types.
Home-page: https://github.com/yasserbdj96/hexor
Author: yasserbdj96
Author-email: yasser.bdj96@gmail.com
License: Apache Software License
Project-URL: Source, https://github.com/yasserbdj96/hexor
Project-URL: WebSite, https://yasserbdj96.github.io/hexor
Project-URL: Chat, https://gitter.im/yasserbdj96/hexor
Project-URL: Author WebSite, https://yasserbdj96.github.io/
Project-URL: Sponsor, https://github.com/sponsors/yasserbdj96
Keywords: yasserbdj96,python,hexor,texts,colors.,hex,background,rgb
Platform: UNKNOWN
Classifier: Environment :: Web Environment
Classifier: Development Status :: 5 - Production/Stable
Classifier: Intended Audience :: Developers
Classifier: Natural Language :: English
Classifier: License :: OSI Approved :: Apache Software License
Classifier: Programming Language :: Python
Classifier: Programming Language :: Python :: 3
Classifier: Programming Language :: Python :: 3.7
Classifier: Programming Language :: Python :: 3.8
Classifier: Programming Language :: Python :: 3.9
Classifier: Programming Language :: Python :: 3.10
Classifier: Programming Language :: Python :: 3 :: Only
Classifier: Operating System :: Unix
Classifier: Operating System :: MacOS :: MacOS X
Classifier: Operating System :: Microsoft :: Windows
Classifier: Topic :: Software Development :: Build Tools
Classifier: Topic :: Software Development :: Libraries
Classifier: Topic :: Software Development :: Libraries :: Python Modules
Classifier: Topic :: Internet :: WWW/HTTP
License-File: LICENSE
